frac_json-0.1.2.dist-info/METADATA
frac_json-0.1.2.dist-info/WHEEL
frac_json/__init__.py
frac_json/__init__.pyi
frac_json/py.typed
frac_json/frac_json.cpython-39-darwin.so
frac_json-0.1.2.dist-info/RECORD
