Metadata-Version: 2.3
Name: frac_json
Version: 0.1.2
Classifier: Programming Language :: Rust
Classifier: Programming Language :: Python :: Implementation :: CPython
Classifier: Programming Language :: Python :: Implementation :: PyPy
Summary: Highly storage efficient binary JSON format
Requires-Python: >=3.8
Project-URL: Source Code, https://github.com/ArthurHeitmann/fractured_binary_json
